Metadata-Version: 2.1
Name: sihle-dsnd-probability
Version: 1.0
Summary: Gaussian and Binomial distributions
Home-page: UNKNOWN
Author: Sihle Wilson
Author-email: sihle.wilson@gmail.com
License: UNKNOWN
Platform: UNKNOWN
